ui_navigate
