Metadata-Version: 1.0
Name: ui-navigate
Version: 1.0.2
Summary: UI navigation library for automation
Home-page: https://github.com/RedHatQE/ui_navigate
Author: Jeff Weiss
Author-email: jweiss@redhat.com
License: PSF
Keywords: automation navigation gui selenium
Platform: UNKNOWN
